{
  "version": "7",
  "dialect": "mysql",
  "entries": [
    {
      "idx": 0,
      "version": "5",
      "when": 1775865958790,
      "tag": "0000_lyrical_prima",
      "breakpoints": true
    },
    {
      "idx": 1,
      "version": "5",
      "when": 1775867734998,
      "tag": "0001_petite_queen_noir",
      "breakpoints": true
    },
    {
      "idx": 2,
      "version": "5",
      "when": 1775867778683,
      "tag": "0002_complex_shotgun",
      "breakpoints": true
    },
    {
      "idx": 3,
      "version": "5",
      "when": 1775915660634,
      "tag": "0003_even_red_ghost",
      "breakpoints": true
    },
    {
      "idx": 4,
      "version": "5",
      "when": 1775936380562,
      "tag": "0004_typical_nico_minoru",
      "breakpoints": true
    }
  ]
}